<manifest alg="2" build="2017.0.4.363" opt="false" iceEnabled="true" iceMarkupVersion="2" iceEnabledOptions="link,responsive,cachebuster,textStyling" exportTarget="other" domain="evilmun.com" resolutions="1x" timestamp="1639934280818">
  <folder name="css">
    <file name="site_global.css" crc="443350757"/>
    <file name="master_______-a.css" crc="3995433978" ref="evilmun-hub---communiti:evilmun-hub---mersh:evilmun-hub---market:evilmun-ewc---egsp.kazan-2021:index:evilmun-hub---ewc-and-lan"/>
    <file name="evilmun-hub---communiti.css" crc="4102913663" ref="evilmun-hub---communiti"/>
    <file name="evilmun-hub---mersh.css" crc="3822976774" ref="evilmun-hub---mersh"/>
    <file name="evilmun-hub---market.css" crc="346440182" ref="evilmun-hub---market"/>
    <file name="evilmun-ewc---egsp_kazan-2021.css" crc="191848516" ref="evilmun-ewc---egsp.kazan-2021"/>
    <file name="index.css" crc="3809642075" ref="index"/>
    <file name="evilmun-hub---ewc-and-lan.css" crc="4061707184" ref="evilmun-hub---ewc-and-lan"/>
  </folder>
  <folder name="fonts">
    <file name="ttcommons-bold.woff" crc="3867701885"/>
    <file name="ttcommons-bold.eot" crc="4117541410"/>
  </folder>
  <folder name="scripts">
    <file name="jquery-1.8.3.min.js" crc="209076791" ref="index:evilmun-ewc---egsp.kazan-2021:evilmun-hub---mersh:evilmun-hub---ewc-and-lan:evilmun-hub---market:evilmun-hub---communiti"/>
    <file name="museutils.js" crc="4216313831" ref="index:evilmun-ewc---egsp.kazan-2021:evilmun-hub---mersh:evilmun-hub---ewc-and-lan:evilmun-hub---market:evilmun-hub---communiti"/>
    <file name="whatinput.js" crc="86476730" ref="index:evilmun-ewc---egsp.kazan-2021:evilmun-hub---mersh:evilmun-hub---ewc-and-lan:evilmun-hub---market:evilmun-hub---communiti"/>
    <file name="museconfig.js" crc="474374037" ref="index:evilmun-ewc---egsp.kazan-2021:evilmun-hub---mersh:evilmun-hub---ewc-and-lan:evilmun-hub---market:evilmun-hub---communiti"/>
    <file name="jquery.musepolyfill.bgsize.js" crc="4110862005" ref="index:evilmun-ewc---egsp.kazan-2021:evilmun-hub---mersh:evilmun-hub---ewc-and-lan:evilmun-hub---market:evilmun-hub---communiti"/>
    <file name="jquery.watch.js" crc="460461809" ref="index:evilmun-ewc---egsp.kazan-2021:evilmun-hub---mersh:evilmun-hub---ewc-and-lan:evilmun-hub---market:evilmun-hub---communiti"/>
    <file name="require.js" crc="3951022091" ref="index:evilmun-ewc---egsp.kazan-2021:evilmun-hub---mersh:evilmun-hub---ewc-and-lan:evilmun-hub---market:evilmun-hub---communiti"/>
    <file name="webpro.js" crc="4143865194" ref="evilmun-ewc---egsp.kazan-2021:evilmun-hub---communiti"/>
    <file name="musewpslideshow.js" crc="3781122836" ref="evilmun-ewc---egsp.kazan-2021:evilmun-hub---communiti"/>
    <file name="jquery.museoverlay.js" crc="4030747646" ref="evilmun-ewc---egsp.kazan-2021:evilmun-hub---communiti"/>
    <file name="touchswipe.js" crc="4200445185" ref="evilmun-ewc---egsp.kazan-2021:evilmun-hub---communiti"/>
  </folder>
  <folder name="images">
    <file name="шаблон-a-favicon.ico" crc="405531321" ref="index"/>
    <file name="loading-logo.png" crc="137666419" ref="index">
      <caption webpage="index" alt=""/>
    </file>
    <file name="evilmun family post vk.jpg" crc="4104097145" ref="index:evilmun-hub---mersh">
      <caption webpage="index" alt=""/>
      <caption webpage="evilmun-hub---mersh" alt=""/>
    </file>
    <file name="asaadas.jpg" crc="4202502796" ref="index">
      <caption webpage="index" alt=""/>
    </file>
    <file name="без цфцвфцв1-u1134-fr.jpg" crc="1380913" ref="index"/>
    <file name="evddd s3.png" crc="131066178" ref="index">
      <caption webpage="index" alt=""/>
    </file>
    <file name="без иsdasdasdмени-1.jpg" crc="4081013934" ref="index">
      <caption webpage="index" alt=""/>
    </file>
    <file name="без fgfgfgfgfg1.jpg" crc="418990029" ref="index">
      <caption webpage="index" alt=""/>
    </file>
    <file name="skin2-u1260-fr.png" crc="4179275883" ref="index"/>
    <file name="фывфывввв.png" crc="445311295" ref="index">
      <caption webpage="index" alt=""/>
    </file>
    <file name="фывфыв-u1263-fr.png" crc="251582496" ref="index"/>
    <file name="skin2.png" crc="4211971210" ref="index">
      <caption webpage="index" alt=""/>
    </file>
    <file name="background.jpg" crc="97092849" ref="index">
      <caption webpage="index" alt=""/>
    </file>
    <file name="чясячсячс.png" crc="383482916" ref="index">
      <caption webpage="index" alt=""/>
    </file>
    <file name="фывфыв.png" crc="4125188141" ref="index">
      <caption webpage="index" alt=""/>
      <caption webpage="index" alt=""/>
      <caption webpage="index" alt=""/>
    </file>
    <file name="ыфвыфвфыв.png" crc="4252304770" ref="index">
      <caption webpage="index" alt=""/>
    </file>
    <file name="ячсячсячс.png" crc="29902783" ref="index">
      <caption webpage="index" alt=""/>
    </file>
    <file name="1 slide.jpg" crc="36838526" ref="index">
      <caption webpage="index" alt=""/>
    </file>
    <file name="android_logo_2019_(stacked)svg.png" crc="195203664" ref="index">
      <caption webpage="index" alt=""/>
    </file>
    <file name="1280px-macos_wordmark_(2017)svg.png" crc="3929925934" ref="index">
      <caption webpage="index" alt=""/>
    </file>
    <file name="windows_10_logosvg.png" crc="500655485" ref="index">
      <caption webpage="index" alt=""/>
    </file>
    <file name="awdadwawd.png" crc="358204436" ref="index:evilmun-hub---communiti">
      <caption webpage="index" alt=""/>
      <caption webpage="evilmun-hub---communiti" alt=""/>
    </file>
    <file name="bookmark-ribbon--v1.png" crc="98427383" ref="index">
      <caption webpage="index" alt=""/>
    </file>
    <file name="cropped-group-4-e1639305818729.png" crc="4286852182" ref="index">
      <caption webpage="index" alt=""/>
    </file>
    <file name="2560px-itchio_logosvg.png" crc="267170424" ref="index">
      <caption webpage="index" alt=""/>
    </file>
    <file name="tuxsvg (1).png" crc="3895778894" ref="index">
      <caption webpage="index" alt=""/>
    </file>
    <file name="dbtid_aachqzx4adzbzibcpy7p4xtzn3unxr-wcoe.png" crc="4039218865" ref="index">
      <caption webpage="index" alt=""/>
      <caption webpage="index" alt=""/>
    </file>
    <file name="1582033937_roy-lichtenstein_vsthemes_ru-11.jpg" crc="3977334541" ref="evilmun-ewc---egsp.kazan-2021">
      <caption webpage="evilmun-ewc---egsp.kazan-2021" alt=""/>
    </file>
    <file name="u191-6.png" crc="103187876" ref="evilmun-ewc---egsp.kazan-2021"/>
    <file name="dfghujk.jpg" crc="3944336811" ref="evilmun-ewc---egsp.kazan-2021">
      <caption webpage="evilmun-ewc---egsp.kazan-2021" alt=""/>
    </file>
    <file name="ыфвфывыфв.png" crc="3801906499" ref="evilmun-ewc---egsp.kazan-2021">
      <caption webpage="evilmun-ewc---egsp.kazan-2021" alt=""/>
    </file>
    <file name="forgors.png" crc="4186751589" seo="true" ref="evilmun-ewc---egsp.kazan-2021">
      <caption webpage="evilmun-ewc---egsp.kazan-2021" alt=""/>
    </file>
    <file name="blank.gif" crc="4208392903" ref="evilmun-ewc---egsp.kazan-2021:evilmun-hub---communiti"/>
    <file name="gg1.png" crc="4021159575" seo="true" ref="evilmun-ewc---egsp.kazan-2021">
      <caption webpage="evilmun-ewc---egsp.kazan-2021" alt=""/>
    </file>
    <file name="gg2.png" crc="228446908" seo="true" ref="evilmun-ewc---egsp.kazan-2021">
      <caption webpage="evilmun-ewc---egsp.kazan-2021" alt=""/>
    </file>
    <file name="gg3.png" crc="3952405587" seo="true" ref="evilmun-ewc---egsp.kazan-2021">
      <caption webpage="evilmun-ewc---egsp.kazan-2021" alt=""/>
    </file>
    <file name="maiisy2.png" crc="4173354019" seo="true" ref="evilmun-ewc---egsp.kazan-2021">
      <caption webpage="evilmun-ewc---egsp.kazan-2021" alt=""/>
    </file>
    <file name="mrtrufilily.png" crc="4143526853" seo="true" ref="evilmun-ewc---egsp.kazan-2021">
      <caption webpage="evilmun-ewc---egsp.kazan-2021" alt=""/>
    </file>
    <file name="popue.png" crc="427344282" seo="true" ref="evilmun-ewc---egsp.kazan-2021">
      <caption webpage="evilmun-ewc---egsp.kazan-2021" alt=""/>
    </file>
    <file name="skovrsj.png" crc="111631557" seo="true" ref="evilmun-ewc---egsp.kazan-2021">
      <caption webpage="evilmun-ewc---egsp.kazan-2021" alt=""/>
    </file>
    <file name="loading.gif" crc="3815509949" ref="evilmun-ewc---egsp.kazan-2021:evilmun-hub---communiti"/>
    <file name="ыываываыва.jpg" crc="198172721" ref="evilmun-hub---mersh">
      <caption webpage="evilmun-hub---mersh" alt=""/>
    </file>
    <file name="twitch.jpg" crc="3787747747" ref="evilmun-hub---ewc-and-lan">
      <caption webpage="evilmun-hub---ewc-and-lan" alt=""/>
      <caption webpage="evilmun-hub---ewc-and-lan" alt=""/>
      <caption webpage="evilmun-hub---ewc-and-lan" alt=""/>
    </file>
    <file name="ыфвфывыфв-u1004-fr.png" crc="4246609467" ref="evilmun-hub---ewc-and-lan"/>
    <file name="gg3-u1008-fr.png" crc="276332158" ref="evilmun-hub---ewc-and-lan"/>
    <file name="forgors-u1006-fr.png" crc="4049100827" ref="evilmun-hub---ewc-and-lan"/>
    <file name="gg1-u1007-fr.png" crc="66537687" ref="evilmun-hub---ewc-and-lan"/>
    <file name="maiisy2-u1009-fr.png" crc="4207453812" ref="evilmun-hub---ewc-and-lan"/>
    <file name="mrtrufilily-u1010-fr.png" crc="4261018756" ref="evilmun-hub---ewc-and-lan"/>
    <file name="twitch-u1092-fr.png" crc="3903855438" ref="evilmun-hub---ewc-and-lan"/>
    <file name="twitch-u1095-fr.png" crc="8501208" ref="evilmun-hub---ewc-and-lan"/>
    <file name="twitch-u1098-fr.png" crc="4269680654" ref="evilmun-hub---ewc-and-lan"/>
    <file name="без цфцвфцв1.jpg" crc="4219727766" ref="evilmun-hub---market">
      <caption webpage="evilmun-hub---market" alt=""/>
    </file>
    <file name="sdfsdfsdf.png" crc="518557230" ref="evilmun-hub---market">
      <caption webpage="evilmun-hub---market" alt=""/>
    </file>
    <file name="без иwadawdawdмени-1.png" crc="233202579" ref="evilmun-hub---market">
      <caption webpage="evilmun-hub---market" alt=""/>
    </file>
    <file name="dsdfsdfsfsdf.png" crc="3920155176" ref="evilmun-hub---market">
      <caption webpage="evilmun-hub---market" alt=""/>
    </file>
    <file name="чмываыва.png" crc="3935194634" ref="evilmun-hub---market">
      <caption webpage="evilmun-hub---market" alt=""/>
    </file>
    <file name="без имыфывыфвени-1.jpg" crc="214743724" seo="true" ref="evilmun-hub---communiti">
      <caption webpage="evilmun-hub---communiti" alt=""/>
    </file>
    <file name="без цфцвфцв1-u1568-fr.jpg" crc="3835744281" ref="evilmun-hub---communiti"/>
    <file name="ысыфвфывфывфывфыв.jpg" crc="4065501202" ref="evilmun-hub---communiti">
      <caption webpage="evilmun-hub---communiti" alt=""/>
    </file>
    <file name="android_logo_2019_(stacked)svg-u1588-fr.png" crc="459085961" ref="evilmun-hub---communiti"/>
    <file name="без ыыыыимени-1.jpg" crc="4169623782" ref="evilmun-hub---communiti">
      <caption webpage="evilmun-hub---communiti" alt=""/>
      <caption webpage="evilmun-hub---communiti" alt=""/>
      <caption webpage="evilmun-hub---communiti" alt=""/>
      <caption webpage="evilmun-hub---communiti" alt=""/>
      <caption webpage="evilmun-hub---communiti" alt=""/>
      <caption webpage="evilmun-hub---communiti" alt=""/>
    </file>
    <file name="ыфвфывыфв-u1662-fr.png" crc="181767708" ref="evilmun-hub---communiti"/>
    <file name="без цфцвфцв1-u1686-fr.jpg" crc="330157328" ref="evilmun-hub---communiti"/>
  </folder>
  <file name="index.html" crc="3908352914" seo="true" mt="1639934245607" redirect="true"/>
  <file name="evilmun-ewc---egsp.kazan-2021.html" crc="3884228569" seo="true" mt="1639934245607" redirect="true"/>
  <file name="evilmun-hub---mersh.html" crc="438174633" seo="true" mt="1639934245607" redirect="true"/>
  <file name="evilmun-hub---ewc-and-lan.html" crc="496738744" seo="true" mt="1639934245607" redirect="true"/>
  <file name="evilmun-hub---market.html" crc="4238715239" seo="true" mt="1639934245607" redirect="true"/>
  <file name="evilmun-hub---communiti.html" crc="291078017" seo="true" mt="1639934245607" redirect="true"/>
</manifest>